{
  "chat": {
    "type": "Nucleus",
    "temperature": 0.8,
    "top_p": 0.5,
    "top_k": 128,
    "presence_penalty": 0.3,
    "frequency_penalty": 0.3,
    "penalty": 400,
    "penalty_decay": 0.99654026
  },
  "reflect": {
    "type": "Mirostat",
    "tau": 0.5,
    "Rate": 0.09
  },
  "task": {
    "type": "Nucleus",
    "temperature": 0.4,
    "top_p": 0.3,
    "top_k": 64,
    "presence_penalty": 0.2,
    "frequency_penalty": 0.2,
    "penalty": 400,
    "penalty_decay": 0.99654026
  },
  "decision": {
    "type": "Nucleus",
    "temperature": 0.3,
    "top_p": 0.2,
    "top_k": 32,
    "presence_penalty": 0.1,
    "frequency_penalty": 0.1,
    "penalty": 400,
    "penalty_decay": 0.99654026
  },
  "creative": {
    "type": "Typical",
    "temperature": 1.0,
    "top_p": 0.7,
    "top_k": 256,
    "tau": 5,
    "presence_penalty": 0.3,
    "frequency_penalty": 0.3,
    "penalty": 400,
    "penalty_decay": 0.99654026
  }
}
